generic_request_signer/__init__.py
generic_request_signer/backend.py
generic_request_signer/check_signature.py
generic_request_signer/client.py
generic_request_signer/constants.py
generic_request_signer/convert_values_to_list.py
generic_request_signer/exceptions.py
generic_request_signer/factory.py
generic_request_signer/request.py
generic_request_signer/response.py
generic_request_signer/tests/__init__.py
generic_request_signer/tests/test_backend.py
generic_request_signer/tests/test_check_signature.py
generic_request_signer/tests/test_client.py
generic_request_signer/tests/test_convert_values_to_list.py
generic_request_signer/tests/test_exceptions.py
generic_request_signer/tests/test_factory.py
generic_request_signer/tests/test_multipart_factory.py
generic_request_signer/tests/test_request.py
generic_request_signer/tests/test_response.py
generic_request_signer-2.0.3.dist-info/licenses/LICENSE
generic_request_signer-2.0.3.dist-info/METADATA
generic_request_signer-2.0.3.dist-info/WHEEL
generic_request_signer-2.0.3.dist-info/top_level.txt
generic_request_signer-2.0.3.dist-info/RECORD
